facekit/__init__.py
facekit/__main__.py
facekit/detectors.py
facekit/loaders.py
facekit/models.py
facekit/schemas.py
facekit-1.1.0.dist-info/LICENSE
facekit-1.1.0.dist-info/METADATA
facekit-1.1.0.dist-info/WHEEL
facekit-1.1.0.dist-info/entry_points.txt
facekit-1.1.0.dist-info/top_level.txt
facekit-1.1.0.dist-info/RECORD
