Metadata-Version: 2.1
Name: facekit
Version: 1.1.0
Summary: Library to ease data collection for face detection/recognition/analysis
Home-page: https://github.com/jarviscodes/facekit
Author: Jarvis Codes
Author-email: jarvis@jayradz.com
License: MIT
Platform: UNKNOWN
Classifier: Programming Language :: Python :: 3.8
License-File: LICENSE
Requires-Dist: click
Requires-Dist: colorama
Requires-Dist: alive-progress
Requires-Dist: mtcnn
